orca_wfrc/__init__.py
orca_wfrc/orca.py
orca_wfrc/server/__init__.py
orca_wfrc/server/server.py
orca_wfrc/utils/__init__.py
orca_wfrc/utils/logutil.py
orca_wfrc/utils/testing.py
orca_wfrc/utils/utils.py
orca_wfrc-0.0.5.dist-info/METADATA
orca_wfrc-0.0.5.dist-info/WHEEL
orca_wfrc-0.0.5.dist-info/entry_points.txt
orca_wfrc-0.0.5.dist-info/top_level.txt
orca_wfrc-0.0.5.dist-info/RECORD
