Metadata-Version: 2.4
Name: orca_wfrc
Version: 0.0.5
Summary: A pipeline orchestration tool with Pandas support, modified by WFRC
Author-email: WFRC_Analytics <joshua.reynolds@wfrc.utah.gov>
License: BSD
Classifier: Development Status :: 4 - Beta
Classifier: Programming Language :: Python :: 2.7
Classifier: Programming Language :: Python :: 3.5
Classifier: Programming Language :: Python :: 3.6
Classifier: Programming Language :: Python :: 3.7
Classifier: Programming Language :: Python :: 3.8
Classifier: License :: OSI Approved :: BSD License
Requires-Python: >=3.5
Requires-Dist: pandas>=0.15.0
Requires-Dist: toolz>=0.8.1
Provides-Extra: server
Requires-Dist: flask>=0.10; extra == "server"
Requires-Dist: pygments>=2.0; extra == "server"
Requires-Dist: six>=1.9.0; extra == "server"
